awssh/__init__.py
awssh/awssh.py
ssh_aws-4.1.6.dist-info/LICENSE
ssh_aws-4.1.6.dist-info/METADATA
ssh_aws-4.1.6.dist-info/WHEEL
ssh_aws-4.1.6.dist-info/entry_points.txt
ssh_aws-4.1.6.dist-info/top_level.txt
ssh_aws-4.1.6.dist-info/RECORD
