Metadata-Version: 2.1
Name: ssh-aws
Version: 4.1.6
Summary: SSH into your EC2 instances.
Home-page: https://gitlab.com/franciscogd/awssh
Author: Francisco Duran
Author-email: franciscogd@gatech.edu
License: UNKNOWN
Download-URL: https://gitlab.com/franciscogd/awssh/archive/4.1.6.tar.gz
Platform: UNKNOWN
Classifier: Programming Language :: Python :: 3
Classifier: License :: OSI Approved :: MIT License
Classifier: Operating System :: OS Independent
Requires-Dist: awscli (>=1.10.14)
Requires-Dist: boto3 (>=1.3.1)
